meson_python-0.17.0.dist-info/METADATA
meson_python-0.17.0.dist-info/WHEEL
meson_python-0.17.0.dist-info/MIT.txt
mesonpy/__init__.py
mesonpy/_compat.py
mesonpy/_editable.py
mesonpy/_rpath.py
mesonpy/_tags.py
mesonpy/_util.py
mesonpy/_wheelfile.py
meson_python-0.17.0.dist-info/RECORD
