Metadata-Version: 2.1
Name: meson-python
Version: 0.17.0
Summary: Meson Python build backend (PEP 517)
Keywords: meson,build,backend,pep517,package
Home-page: https://github.com/mesonbuild/meson-python
Maintainer-Email: Ralf Gommers <ralf.gommers@gmail.com>, Daniele Nicolodi <daniele@grinta.net>, Henry Schreiner <HenrySchreinerIII@gmail.com>, Thomas Li <47963215+lithomas1@users.noreply.github.com>
License: Copyright © 2022 the meson-python contributors
Classifier: Development Status :: 5 - Production/Stable
Classifier: Programming Language :: Python
Classifier: Topic :: Software Development :: Build Tools
Project-URL: Homepage, https://github.com/mesonbuild/meson-python
Project-URL: Repository, https://github.com/mesonbuild/meson-python
Project-URL: Documentation, https://mesonbuild.com/meson-python/
Project-URL: Changelog, https://mesonbuild.com/meson-python/changelog.html
Requires-Python: >=3.7
Requires-Dist: meson>=0.63.3; python_version < "3.12"
Requires-Dist: meson>=1.2.3; python_version >= "3.12"
Requires-Dist: packaging>=19.0
Requires-Dist: pyproject-metadata>=0.7.1
Requires-Dist: tomli>=1.0.0; python_version < "3.11"
Requires-Dist: build; extra == "test"
Requires-Dist: pytest>=6.0; extra == "test"
Requires-Dist: pytest-cov[toml]; extra == "test"
Requires-Dist: pytest-mock; extra == "test"
Requires-Dist: cython>=3.0.3; extra == "test"
Requires-Dist: wheel; extra == "test"
Requires-Dist: typing-extensions>=3.7.4; python_version < "3.11" and extra == "test"
Requires-Dist: furo>=2023.5.20; extra == "docs"
Requires-Dist: sphinx~=6.2; extra == "docs"
Requires-Dist: sphinx-copybutton>=0.5.0; extra == "docs"
Requires-Dist: sphinx-design>=0.1.0; extra == "docs"
Requires-Dist: sphinxext-opengraph>=0.7.0; extra == "docs"
Provides-Extra: test
Provides-Extra: docs
